napari_spofi/__init__.py
napari_spofi/_annotation.py
napari_spofi/_data_handler.py
napari_spofi/_prediction.py
napari_spofi/_training.py
napari_spofi/_widget.py
napari_spofi/napari.yaml
napari_spofi/_tests/__init__.py
napari_spofi/_tests/test_widget.py
napari_spofi/resources/__init__.py
napari_spofi/resources/spofi_defaults.json
napari_spofi/resources/styles.qss
napari_spofi/spofi_utils/__init__.py
napari_spofi/spofi_utils/directory_maker.py
napari_spofi/spofi_utils/normalizer.py
napari_spofi/spofi_utils/prediction_utils.py
napari_spofi/spofi_utils/training_utils.py
napari_spofi-0.0.1.dist-info/LICENSE
napari_spofi-0.0.1.dist-info/METADATA
napari_spofi-0.0.1.dist-info/WHEEL
napari_spofi-0.0.1.dist-info/entry_points.txt
napari_spofi-0.0.1.dist-info/top_level.txt
napari_spofi-0.0.1.dist-info/RECORD
