Metadata-Version: 2.1
Name: napari-spofi
Version: 0.0.1
Summary: napari plugin to interactively train and test a StarDist model
Author: Christian Schulze
Author-email: drchrisch@gmail.com
License: BSD-3-Clause
Project-URL: Bug Tracker, https://github.com/drchrisch/napari-spofi/issues
Project-URL: Documentation, https://github.com/drchrisch/napari-spofi#README.md
Project-URL: Source Code, https://github.com/drchrisch/napari-spofi
Project-URL: User Support, https://github.com/drchrisch/napari-spofi/issues
Classifier: Development Status :: 2 - Pre-Alpha
Classifier: Framework :: napari
Classifier: Intended Audience :: Developers
Classifier: License :: OSI Approved :: BSD License
Classifier: Operating System :: OS Independent
Classifier: Programming Language :: Python
Classifier: Programming Language :: Python :: 3
Classifier: Programming Language :: Python :: 3 :: Only
Classifier: Programming Language :: Python :: 3.8
Classifier: Programming Language :: Python :: 3.9
Classifier: Programming Language :: Python :: 3.10
Classifier: Topic :: Scientific/Engineering :: Image Processing
Classifier: Topic :: Scientific/Engineering :: Visualization
Requires-Python: >=3.8
License-File: LICENSE
Requires-Dist: numpy
Requires-Dist: pandas
Requires-Dist: magicgui
Requires-Dist: qtpy
Requires-Dist: scikit-image
Requires-Dist: pyclesperanto
Requires-Dist: tensorflow
Requires-Dist: stardist
Provides-Extra: testing
Requires-Dist: tox ; extra == 'testing'
Requires-Dist: napari ; extra == 'testing'
Requires-Dist: pyqt5 ; extra == 'testing'
